[
  {
    "elements": [
      {
        "id": "login;login-with-correct-username-and-password",
        "keyword": "Scenario",
        "line": 4,
        "name": "Login with correct username and password",
        "steps": [
          {
            "arguments": [],
            "keyword": "Given ",
            "name": "I go to amazon home page",
            "result": {
              "status": "passed",
              "duration": 3664853314
            },
            "line": 5,
            "match": {
              "location": "/Users/twer/Documents/Work/Peacock/e2e-test-nodejs/step-definitions/amazon-purchase-steps.js:2"
            }
          },
          {
            "arguments": [],
            "keyword": "When ",
            "name": "I login with username \"15109242187\" and password \"q1w2e3R$\"",
            "result": {
              "status": "passed",
              "duration": 9283706037
            },
            "line": 6,
            "match": {
              "location": "/Users/twer/Documents/Work/Peacock/e2e-test-nodejs/step-definitions/amazon-purchase-steps.js:6"
            }
          },
          {
            "arguments": [],
            "keyword": "Then ",
            "name": "I should see the account name is \"xu xiaojuan\"",
            "result": {
              "status": "passed",
              "duration": 1291743
            },
            "line": 7,
            "match": {
              "location": "/Users/twer/Documents/Work/Peacock/e2e-test-nodejs/step-definitions/amazon-purchase-steps.js:10"
            }
          },
          {
            "arguments": [],
            "keyword": "After ",
            "result": {
              "status": "passed",
              "duration": 57393323
            },
            "hidden": true,
            "match": {
              "location": "/Users/twer/Documents/Work/Peacock/e2e-test-nodejs/runtime/world.js:193"
            }
          }
        ],
        "tags": [
          {
            "name": "@purchase",
            "line": 1
          }
        ],
        "type": "scenario"
      }
    ],
    "id": "login",
    "keyword": "Feature",
    "line": 2,
    "name": "Login",
    "tags": [
      {
        "name": "@purchase",
        "line": 1
      }
    ],
    "uri": "/Users/twer/Documents/Work/Peacock/e2e-test-nodejs/features/amazon-purchase.feature"
  }
]